jyapystock/__init__.py
jyapystock/alpha_vantage_support.py
jyapystock/nasdaq_support.py
jyapystock/nse_support.py
jyapystock/nyse_support.py
jyapystock/stock_price_provider.py
jyapystock/yfinance_support.py
jyapystock-0.3.3.dist-info/licenses/LICENSE
jyapystock-0.3.3.dist-info/METADATA
jyapystock-0.3.3.dist-info/WHEEL
jyapystock-0.3.3.dist-info/top_level.txt
jyapystock-0.3.3.dist-info/RECORD
