Metadata-Version: 2.4
Name: jyapystock
Version: 0.3.3
Summary: Fetch live and historical stock prices for Indian and American exchanges.
Author: krishna
Maintainer: krishna
License-Expression: MIT
Project-URL: Homepage, https://example.org/jyapystock
Keywords: stocks,finance,yfinance,alpha-vantage,market-data
Classifier: Development Status :: 4 - Beta
Classifier: Intended Audience :: Developers
Classifier: Programming Language :: Python :: 3
Classifier: Programming Language :: Python :: 3 :: Only
Classifier: Programming Language :: Python :: 3.8
Classifier: Programming Language :: Python :: 3.9
Classifier: Programming Language :: Python :: 3.10
Classifier: Programming Language :: Python :: 3.11
Classifier: Topic :: Software Development :: Libraries
Requires-Python: >=3.8
License-File: LICENSE
Requires-Dist: yfinance<0.3,>=0.2.27
Requires-Dist: requests<3,>=2.28
Requires-Dist: pandas<3,>=1.5
Requires-Dist: nse<3,>=2.0.0
Provides-Extra: dev
Requires-Dist: pytest>=7.0; extra == "dev"
Requires-Dist: pytest-cov; extra == "dev"
Requires-Dist: flake8; extra == "dev"
Dynamic: license-file
